checkin/__init__.py
checkin/admin.html
checkin/admin.py
checkin/checkin.html
checkin/server.py
ciit_checkin-0.1.1.dist-info/licenses/LICENSE
ciit_checkin-0.1.1.dist-info/METADATA
ciit_checkin-0.1.1.dist-info/WHEEL
ciit_checkin-0.1.1.dist-info/entry_points.txt
ciit_checkin-0.1.1.dist-info/top_level.txt
ciit_checkin-0.1.1.dist-info/RECORD
